observatory_mcp/__init__.py
observatory_mcp/client.py
observatory_mcp/config.py
observatory_mcp/exceptions.py
observatory_mcp/interceptor.py
observatory_mcp/models.py
observatory_mcp/privacy.py
observatory_mcp/sdk.py
observatory_mcp/utils.py
observatory_mcp-0.0.2.dev0.dist-info/licenses/LICENSE
observatory_mcp-0.0.2.dev0.dist-info/METADATA
observatory_mcp-0.0.2.dev0.dist-info/WHEEL
observatory_mcp-0.0.2.dev0.dist-info/top_level.txt
observatory_mcp-0.0.2.dev0.dist-info/RECORD
