Metadata-Version: 2.4
Name: observatory-mcp
Version: 0.0.2.dev0
Summary: Observatory SDK for MCP server analytics and monitoring - Add comprehensive observability to your MCP servers with just 2 lines of code
Author-email: Observatory Team <team@observatory.dev>
Maintainer-email: Observatory Team <team@observatory.dev>
License: MIT
Project-URL: Homepage, https://observatory.dev
Project-URL: Documentation, https://observatory.dev/docs/python-sdk
Project-URL: Repository, https://github.com/observatory/observatory
Project-URL: Issues, https://github.com/observatory/observatory/issues
Project-URL: Changelog, https://github.com/observatory/observatory/blob/main/CHANGELOG.md
Keywords: mcp,model-context-protocol,observability,analytics,monitoring,telemetry,metrics,tracking,sdk
Classifier: Development Status :: 4 - Beta
Classifier: Intended Audience :: Developers
Classifier: License :: OSI Approved :: MIT License
Classifier: Operating System :: OS Independent
Classifier: Programming Language :: Python :: 3
Classifier: Programming Language :: Python :: 3.10
Classifier: Programming Language :: Python :: 3.11
Classifier: Programming Language :: Python :: 3.12
Classifier: Topic :: Software Development :: Libraries :: Python Modules
Classifier: Topic :: System :: Monitoring
Classifier: Typing :: Typed
Requires-Python: >=3.10
License-File: LICENSE
Requires-Dist: httpx>=0.24.0
Requires-Dist: pydantic>=2.0.0
Provides-Extra: mcp
Requires-Dist: mcp>=0.9.0; extra == "mcp"
Provides-Extra: dev
Requires-Dist: mcp>=0.9.0; extra == "dev"
Requires-Dist: pytest>=7.0; extra == "dev"
Requires-Dist: pytest-asyncio>=0.21.0; extra == "dev"
Requires-Dist: pytest-cov>=4.0; extra == "dev"
Requires-Dist: black>=23.0; extra == "dev"
Requires-Dist: mypy>=1.0; extra == "dev"
Requires-Dist: ruff>=0.1.0; extra == "dev"
Requires-Dist: build>=1.0.0; extra == "dev"
Requires-Dist: twine>=4.0.0; extra == "dev"
Provides-Extra: all
Requires-Dist: mcp>=0.9.0; extra == "all"
Requires-Dist: psutil>=5.9.0; extra == "all"
Dynamic: license-file
